async_rediscache/__init__.py
async_rediscache/session.py
async_rediscache/redis_scripts/__init__.py
async_rediscache/redis_scripts/rediscache_increment.lua
async_rediscache/redis_scripts/rediscache_pop.lua
async_rediscache/redis_scripts/redisqueue_reschedule_all_client_tasks.lua
async_rediscache/redis_scripts/redisqueue_reschedule_task.lua
async_rediscache/types/__init__.py
async_rediscache/types/base.py
async_rediscache/types/cache.py
async_rediscache/types/queue.py
async_rediscache-0.2.0.dist-info/METADATA
async_rediscache-0.2.0.dist-info/WHEEL
async_rediscache-0.2.0.dist-info/top_level.txt
async_rediscache-0.2.0.dist-info/RECORD
