Metadata-Version: 2.1
Name: async-rediscache
Version: 0.2.0
Summary: An easy to use asynchronous Redis cache
Home-page: https://github.com/python-discord/async-rediscache
Author: Python Discord
Author-email: staff@pythondiscord.com
License: MIT
Platform: UNKNOWN
Classifier: License :: OSI Approved :: MIT License
Classifier: Development Status :: 4 - Beta
Classifier: Operating System :: OS Independent
Classifier: Programming Language :: Python
Classifier: Programming Language :: Python :: 3.7
Classifier: Programming Language :: Python :: 3.8
Classifier: Programming Language :: Python :: 3.9
Classifier: Framework :: AsyncIO
Classifier: Topic :: Database
Classifier: Topic :: Software Development :: Libraries :: Python Modules
Requires-Python: ~=3.7
Requires-Dist: aioredis (>=1)
Provides-Extra: fakeredis
Requires-Dist: fakeredis[lua] (>=1.4.4) ; extra == 'fakeredis'
